README.txt
setup.py
TracLoginRequiredPlugin.egg-info/PKG-INFO
TracLoginRequiredPlugin.egg-info/SOURCES.txt
TracLoginRequiredPlugin.egg-info/dependency_links.txt
TracLoginRequiredPlugin.egg-info/entry_points.txt
TracLoginRequiredPlugin.egg-info/requires.txt
TracLoginRequiredPlugin.egg-info/top_level.txt
loginrequired/__init__.py