Metadata-Version: 1.0
Name: TracLoginRequiredPlugin
Version: 0.1.0
Summary: Trac plugin which redirects all unauthenticated requests to the login page
Home-page: https://code.google.com/p/tracloginrequiredplugin/
Author: David A. Riggs
Author-email: david.riggs@createtank.com
License: UNKNOWN
Download-URL: https://code.google.com/p/tracloginrequiredplugin/
Platform: UNKNOWN
Classifier: Development Status :: 3 - Alpha
Classifier: Environment :: Plugins
Classifier: Framework :: Trac
Classifier: Intended Audience :: System Administrators
Classifier: License :: OSI Approved :: GNU General Public License (GPL)
Classifier: Natural Language :: English
Classifier: Operating System :: OS Independent
Classifier: Programming Language :: Python
Classifier: Programming Language :: Python :: 2
Classifier: Programming Language :: Python :: 2.5
Classifier: Topic :: System :: Systems Administration :: Authentication/Directory
